MongoDBProxy-0.1.0.dist-info/DESCRIPTION.rst
MongoDBProxy-0.1.0.dist-info/METADATA
MongoDBProxy-0.1.0.dist-info/RECORD
MongoDBProxy-0.1.0.dist-info/WHEEL
MongoDBProxy-0.1.0.dist-info/metadata.json
MongoDBProxy-0.1.0.dist-info/top_level.txt
mongo_proxy/__init__.py
mongo_proxy/durable_cursor.py
mongo_proxy/mongodb_proxy.py
