Metadata-Version: 2.0
Name: MongoDBProxy
Version: 0.1.0
Summary: Proxy around MongoDB connection that automatically handles AutoReconnect exceptions.
Home-page: https://github.com/arngarden/MongoDBProxy
Author: Gustav Arngarden
Author-email: UNKNOWN
License: UNKNOWN
Platform: UNKNOWN
Classifier: License :: OSI Approved :: Apache Software License
Requires-Dist: pymongo
